<?xml version="1.0" encoding="utf-8"?>
<LanguageData>

  <Android2Tier.label>андроид Т2</Android2Tier.label>
  <Android2Tier.description>Несколько продвинутый андроид, способный почти идеально сохранять сознание ИИ с разумными уровнями моторных навыков. Хороший андроид, который широко используется на мирах утопиях для базового обслуживания и уборки.</Android2Tier.description>
  <Android2Tier.tools.0.label>правый кулак</Android2Tier.tools.0.label>
  <Android2Tier.tools.1.label>левый кулак</Android2Tier.tools.1.label>
  <Android2Tier.tools.2.label>голова</Android2Tier.tools.2.label>


</LanguageData>